github_enterprise_mcp/__init__.py
github_enterprise_mcp/server.py
github_enterprise_mcp-0.2.0.dist-info/METADATA
github_enterprise_mcp-0.2.0.dist-info/WHEEL
github_enterprise_mcp-0.2.0.dist-info/entry_points.txt
github_enterprise_mcp-0.2.0.dist-info/RECORD
