Metadata-Version: 2.4
Name: github-enterprise-mcp
Version: 0.2.0
Summary: An MCP server for GitHub Enterprise that handles repository access, branch creation, commits, and pushes
Author-email: akhilthomas236 <akhilthomas236@gmail.com>
Requires-Python: >=3.12
Requires-Dist: mcp>=1.9.4
Requires-Dist: pygithub>=2.6.0
Requires-Dist: requests>=2.32.0
